{
  "k1": "v",
  "k10": "v",
  "k100": "v",
  "k102": "v",
  "k104": "v",
  "k106": "v",
  "k108": "v",
  "k111": "v",
  "k113": "v",
  "k115": "v",
  "k117": "v",
  "k119": "v",
  "k12": "v",
  "k120": "v",
  "k122": "v",
  "k124": "v",
  "k126": "v",
  "k128": "v",
  "k131": "v",
  "k133": "v",
  "k135": "v",
  "k137": "v",
  "k139": "v",
  "k14": "v",
  "k140": "v",
  "k142": "v",
  "k144": "v",
  "k146": "v",
  "k148": "v",
  "k151": "v",
  "k153": "v",
  "k155": "v",
  "k157": "v",
  "k159": "v",
  "k16": "v",
  "k160": "v",
  "k162": "v",
  "k164": "v",
  "k166": "v",
  "k168": "v",
  "k171": "v",
  "k173": "v",
  "k175": "v",
  "k177": "v",
  "k179": "v",
  "k18": "v",
  "k180": "v",
  "k182": "v",
  "k184": "v",
  "k186": "v",
  "k188": "v",
  "k191": "v",
  "k193": "v",
  "k195": "v",
  "k197": "v",
  "k199": "v",
  "k201": "v",
  "k203": "v",
  "k205": "v",
  "k207": "v",
  "k209": "v",
  "k21": "v",
  "k210": "v",
  "k212": "v",
  "k214": "v",
  "k216": "v",
  "k218": "v",
  "k221": "v",
  "k223": "v",
  "k225": "v",
  "k227": "v",
  "k229": "v",
  "k23": "v",
  "k230": "v",
  "k232": "v",
  "k234": "v",
  "k236": "v",
  "k238": "v",
  "k241": "v",
  "k243": "v",
  "k245": "v",
  "k247": "v",
  "k249": "v",
  "k25": "v",
  "k250": "v",
  "k252": "v",
  "k254": "v",
  "k256": "v",
  "k258": "v",
  "k261": "v",
  "k263": "v",
  "k265": "v",
  "k267": "v",
  "k269": "v",
  "k27": "v",
  "k270": "v",
  "k272": "v",
  "k274": "v",
  "k276": "v",
  "k278": "v",
  "k281": "v",
  "k283": "v",
  "k285": "v",
  "k287": "v",
  "k289": "v",
  "k29": "v",
  "k290": "v",
  "k292": "v",
  "k294": "v",
  "k296": "v",
  "k298": "v",
  "k3": "v",
  "k30": "v",
  "k300": "v",
  "k302": "v",
  "k304": "v",
  "k306": "v",
  "k308": "v",
  "k311": "v",
  "k313": "v",
  "k315": "v",
  "k317": "v",
  "k319": "v",
  "k32": "v",
  "k320": "v",
  "k322": "v",
  "k324": "v",
  "k326": "v",
  "k328": "v",
  "k331": "v",
  "k333": "v",
  "k335": "v",
  "k337": "v",
  "k339": "v",
  "k34": "v",
  "k340": "v",
  "k342": "v",
  "k344": "v",
  "k346": "v",
  "k348": "v",
  "k351": "v",
  "k353": "v",
  "k355": "v",
  "k357": "v",
  "k359": "v",
  "k36": "v",
  "k360": "v",
  "k362": "v",
  "k364": "v",
  "k366": "v",
  "k368": "v",
  "k371": "v",
  "k373": "v",
  "k375": "v",
  "k377": "v",
  "k379": "v",
  "k38": "v",
  "k380": "v",
  "k382": "v",
  "k384": "v",
  "k386": "v",
  "k388": "v",
  "k391": "v",
  "k393": "v",
  "k395": "v",
  "k397": "v",
  "k399": "v",
  "k401": "v",
  "k403": "v",
  "k405": "v",
  "k407": "v",
  "k409": "v",
  "k41": "v",
  "k410": "v",
  "k412": "v",
  "k414": "v",
  "k416": "v",
  "k418": "v",
  "k421": "v",
  "k423": "v",
  "k425": "v",
  "k427": "v",
  "k429": "v",
  "k43": "v",
  "k430": "v",
  "k432": "v",
  "k434": "v",
  "k436": "v",
  "k438": "v",
  "k441": "v",
  "k443": "v",
  "k445": "v",
  "k447": "v",
  "k449": "v",
  "k45": "v",
  "k450": "v",
  "k452": "v",
  "k454": "v",
  "k456": "v",
  "k458": "v",
  "k461": "v",
  "k463": "v",
  "k465": "v",
  "k467": "v",
  "k469": "v",
  "k47": "v",
  "k470": "v",
  "k472": "v",
  "k474": "v",
  "k476": "v",
  "k478": "v",
  "k481": "v",
  "k483": "v",
  "k485": "v",
  "k487": "v",
  "k489": "v",
  "k49": "v",
  "k490": "v",
  "k492": "v",
  "k494": "v",
  "k496": "v",
  "k498": "v",
  "k5": "v",
  "k50": "v",
  "k500": "v",
  "k502": "v",
  "k504": "v",
  "k506": "v",
  "k508": "v",
  "k511": "v",
  "k513": "v",
  "k515": "v",
  "k517": "v",
  "k519": "v",
  "k52": "v",
  "k520": "v",
  "k522": "v",
  "k524": "v",
  "k526": "v",
  "k528": "v",
  "k531": "v",
  "k533": "v",
  "k535": "v",
  "k537": "v",
  "k539": "v",
  "k54": "v",
  "k540": "v",
  "k542": "v",
  "k544": "v",
  "k546": "v",
  "k548": "v",
  "k551": "v",
  "k553": "v",
  "k555": "v",
  "k557": "v",
  "k559": "v",
  "k56": "v",
  "k560": "v",
  "k562": "v",
  "k564": "v",
  "k566": "v",
  "k568": "v",
  "k571": "v",
  "k573": "v",
  "k575": "v",
  "k577": "v",
  "k579": "v",
  "k58": "v",
  "k580": "v",
  "k582": "v",
  "k584": "v",
  "k586": "v",
  "k588": "v",
  "k591": "v",
  "k593": "v",
  "k595": "v",
  "k597": "v",
  "k599": "v",
  "k601": "v",
  "k603": "v",
  "k605": "v",
  "k607": "v",
  "k609": "v",
  "k61": "v",
  "k610": "v",
  "k612": "v",
  "k614": "v",
  "k616": "v",
  "k618": "v",
  "k621": "v",
  "k623": "v",
  "k625": "v",
  "k627": "v",
  "k629": "v",
  "k63": "v",
  "k630": "v",
  "k632": "v",
  "k634": "v",
  "k636": "v",
  "k638": "v",
  "k641": "v",
  "k643": "v",
  "k645": "v",
  "k647": "v",
  "k649": "v",
  "k65": "v",
  "k650": "v",
  "k652": "v",
  "k654": "v",
  "k656": "v",
  "k658": "v",
  "k661": "v",
  "k663": "v",
  "k665": "v",
  "k667": "v",
  "k669": "v",
  "k67": "v",
  "k670": "v",
  "k672": "v",
  "k674": "v",
  "k676": "v",
  "k678": "v",
  "k681": "v",
  "k683": "v",
  "k685": "v",
  "k687": "v",
  "k689": "v",
  "k69": "v",
  "k690": "v",
  "k692": "v",
  "k694": "v",
  "k696": "v",
  "k698": "v",
  "k7": "v",
  "k70": "v",
  "k700": "v",
  "k702": "v",
  "k704": "v",
  "k706": "v",
  "k708": "v",
  "k711": "v",
  "k713": "v",
  "k715": "v",
  "k717": "v",
  "k719": "v",
  "k72": "v",
  "k720": "v",
  "k722": "v",
  "k724": "v",
  "k726": "v",
  "k728": "v",
  "k731": "v",
  "k733": "v",
  "k735": "v",
  "k737": "v",
  "k739": "v",
  "k74": "v",
  "k740": "v",
  "k742": "v",
  "k744": "v",
  "k746": "v",
  "k748": "v",
  "k751": "v",
  "k753": "v",
  "k755": "v",
  "k757": "v",
  "k759": "v",
  "k76": "v",
  "k760": "v",
  "k762": "v",
  "k764": "v",
  "k766": "v",
  "k768": "v",
  "k771": "v",
  "k773": "v",
  "k775": "v",
  "k777": "v",
  "k779": "v",
  "k78": "v",
  "k780": "v",
  "k782": "v",
  "k784": "v",
  "k786": "v",
  "k788": "v",
  "k791": "v",
  "k793": "v",
  "k795": "v",
  "k797": "v",
  "k799": "v",
  "k801": "v",
  "k803": "v",
  "k805": "v",
  "k807": "v",
  "k809": "v",
  "k81": "v",
  "k810": "v",
  "k812": "v",
  "k814": "v",
  "k816": "v",
  "k818": "v",
  "k821": "v",
  "k823": "v",
  "k825": "v",
  "k827": "v",
  "k829": "v",
  "k83": "v",
  "k830": "v",
  "k832": "v",
  "k834": "v",
  "k836": "v",
  "k838": "v",
  "k841": "v",
  "k843": "v",
  "k845": "v",
  "k847": "v",
  "k849": "v",
  "k85": "v",
  "k850": "v",
  "k852": "v",
  "k854": "v",
  "k856": "v",
  "k858": "v",
  "k861": "v",
  "k863": "v",
  "k865": "v",
  "k867": "v",
  "k869": "v",
  "k87": "v",
  "k870": "v",
  "k872": "v",
  "k874": "v",
  "k876": "v",
  "k878": "v",
  "k881": "v",
  "k883": "v",
  "k885": "v",
  "k887": "v",
  "k889": "v",
  "k89": "v",
  "k890": "v",
  "k892": "v",
  "k894": "v",
  "k896": "v",
  "k898": "v",
  "k9": "v",
  "k90": "v",
  "k900": "v",
  "k902": "v",
  "k904": "v",
  "k906": "v",
  "k908": "v",
  "k911": "v",
  "k913": "v",
  "k915": "v",
  "k917": "v",
  "k919": "v",
  "k92": "v",
  "k920": "v",
  "k922": "v",
  "k924": "v",
  "k926": "v",
  "k928": "v",
  "k931": "v",
  "k933": "v",
  "k935": "v",
  "k937": "v",
  "k939": "v",
  "k94": "v",
  "k940": "v",
  "k942": "v",
  "k944": "v",
  "k946": "v",
  "k948": "v",
  "k951": "v",
  "k953": "v",
  "k955": "v",
  "k957": "v",
  "k959": "v",
  "k96": "v",
  "k960": "v",
  "k962": "v",
  "k964": "v",
  "k966": "v",
  "k968": "v",
  "k971": "v",
  "k973": "v",
  "k975": "v",
  "k977": "v",
  "k979": "v",
  "k98": "v",
  "k980": "v",
  "k982": "v",
  "k984": "v",
  "k986": "v",
  "k988": "v",
  "k991": "v",
  "k993": "v",
  "k995": "v",
  "k997": "v",
  "k999": "v"
}